LICENSE.txt
MANIFEST.in
README.md
setup.py
neuronflow/__init__.py
neuronflow/classifier.py
neuronflow/metrics.py
neuronflow/regression.py
neuronflow/utility.py
neuronflow.egg-info/PKG-INFO
neuronflow.egg-info/SOURCES.txt
neuronflow.egg-info/dependency_links.txt
neuronflow.egg-info/requires.txt
neuronflow.egg-info/top_level.txt