Metadata-Version: 2.1
Name: neuronflow
Version: 0.1.2
Summary: UNKNOWN
Home-page: UNKNOWN
Author: Riddhick Dalal
Author-email: riddhick14@gmail.com
License: UNKNOWN
Platform: UNKNOWN
Classifier: Programming Language :: Python :: 3
Classifier: License :: OSI Approved :: MIT License
Requires-Python: >=3.6
License-File: LICENSE.txt
